gigalens/__init__.py
gigalens/inference.py
gigalens/model.py
gigalens/profile.py
gigalens/simulator.py
gigalens/assets/demo.npy
gigalens/assets/psf.npy
gigalens/jax/__init__.py
gigalens/jax/inference.py
gigalens/jax/model.py
gigalens/jax/simulator.py
gigalens/jax/profiles/__init__.py
gigalens/jax/profiles/light/__init__.py
gigalens/jax/profiles/light/sersic.py
gigalens/jax/profiles/light/shapelets.py
gigalens/jax/profiles/mass/__init__.py
gigalens/jax/profiles/mass/epl.py
gigalens/jax/profiles/mass/shear.py
gigalens/jax/profiles/mass/sie.py
gigalens/jax/profiles/mass/sis.py
gigalens/jax/profiles/mass/tnfw.py
gigalens/tf/__init__.py
gigalens/tf/inference.py
gigalens/tf/model.py
gigalens/tf/simulator.py
gigalens/tf/profiles/__init__.py
gigalens/tf/profiles/light/__init__.py
gigalens/tf/profiles/light/sersic.py
gigalens/tf/profiles/light/shapelets.py
gigalens/tf/profiles/mass/__init__.py
gigalens/tf/profiles/mass/epl.py
gigalens/tf/profiles/mass/shear.py
gigalens/tf/profiles/mass/sie.py
gigalens/tf/profiles/mass/sis.py
gigalens/tf/profiles/mass/tnfw.py
gigalens-0.1.8.dist-info/LICENSE
gigalens-0.1.8.dist-info/METADATA
gigalens-0.1.8.dist-info/WHEEL
gigalens-0.1.8.dist-info/top_level.txt
gigalens-0.1.8.dist-info/RECORD
