Metadata-Version: 2.1
Name: gigalens
Version: 0.1.8
Summary: Fast strong gravitational lens modeling
Author: Andi Gu
Author-email: andi.gu@berkeley.edu
License: MIT
Classifier: Development Status :: 3 - Alpha
Classifier: License :: OSI Approved :: MIT License
Classifier: Programming Language :: Python :: 3.7
License-File: LICENSE
Requires-Dist: tensorflow (>=2.6.0)
Requires-Dist: tensorflow-probability (>=0.15.0)
Requires-Dist: lenstronomy (==1.9.3)
Requires-Dist: scikit-image (==0.18.2)
Requires-Dist: cosmohammer (==0.6.1)
Requires-Dist: schwimmbad (==0.3.2)
Requires-Dist: dynesty (==1.1)
Requires-Dist: corner (==2.2.1)
Requires-Dist: mpmath (==1.2.1)
Requires-Dist: tqdm (==4.62.0)
Provides-Extra: jax
Requires-Dist: jax (==0.2.24) ; extra == 'jax'
Requires-Dist: optax (==0.0.9) ; extra == 'jax'
Requires-Dist: objax (==1.4.0) ; extra == 'jax'
Provides-Extra: test
Requires-Dist: coverage ; extra == 'test'
Requires-Dist: pytest ; extra == 'test'
Requires-Dist: jax (==0.2.24) ; extra == 'test'
Requires-Dist: optax (==0.0.9) ; extra == 'test'
Requires-Dist: objax (==1.4.0) ; extra == 'test'
